cashu/__init__.py
cashu/core/__init__.py
cashu/core/base.py
cashu/core/crypto/__init__.py
cashu/core/crypto/aes.py
cashu/core/crypto/b_dhke.py
cashu/core/crypto/keys.py
cashu/core/crypto/secp.py
cashu/core/db.py
cashu/core/errors.py
cashu/core/helpers.py
cashu/core/htlc.py
cashu/core/json_rpc/base.py
cashu/core/legacy.py
cashu/core/logging.py
cashu/core/migrations.py
cashu/core/mint_info.py
cashu/core/models.py
cashu/core/nuts/__init__.py
cashu/core/nuts/nut14.py
cashu/core/nuts/nut20.py
cashu/core/nuts/nuts.py
cashu/core/p2pk.py
cashu/core/secret.py
cashu/core/settings.py
cashu/core/split.py
cashu/lightning/__init__.py
cashu/lightning/base.py
cashu/lightning/blink.py
cashu/lightning/clnrest.py
cashu/lightning/corelightningrest.py
cashu/lightning/fake.py
cashu/lightning/lnbits.py
cashu/lightning/lnd_grpc/lnd_grpc.py
cashu/lightning/lnd_grpc/protos/download_and_build.sh
cashu/lightning/lnd_grpc/protos/lightning.proto
cashu/lightning/lnd_grpc/protos/lightning_pb2.py
cashu/lightning/lnd_grpc/protos/lightning_pb2.pyi
cashu/lightning/lnd_grpc/protos/lightning_pb2_grpc.py
cashu/lightning/lnd_grpc/protos/lightning_pb2_grpc.pyi
cashu/lightning/lnd_grpc/protos/router.proto
cashu/lightning/lnd_grpc/protos/router_pb2.py
cashu/lightning/lnd_grpc/protos/router_pb2.pyi
cashu/lightning/lnd_grpc/protos/router_pb2_grpc.py
cashu/lightning/lnd_grpc/protos/router_pb2_grpc.pyi
cashu/lightning/lndrest.py
cashu/lightning/macaroon.py
cashu/lightning/strike.py
cashu/mint/__init__.py
cashu/mint/__main__.py
cashu/mint/app.py
cashu/mint/auth/base.py
cashu/mint/auth/crud.py
cashu/mint/auth/migrations.py
cashu/mint/auth/router.py
cashu/mint/auth/server.py
cashu/mint/cache.py
cashu/mint/conditions.py
cashu/mint/crud.py
cashu/mint/db/read.py
cashu/mint/db/write.py
cashu/mint/encrypt.py
cashu/mint/events/__init__.py
cashu/mint/events/client.py
cashu/mint/events/event_model.py
cashu/mint/events/events.py
cashu/mint/features.py
cashu/mint/keysets.py
cashu/mint/ledger.py
cashu/mint/limit.py
cashu-0.18.1.dist-info/LICENSE.md
cashu-0.18.1.dist-info/METADATA
cashu-0.18.1.dist-info/WHEEL
cashu-0.18.1.dist-info/entry_points.txt
cashu-0.18.1.dist-info/RECORD
